llm_context/__init__.py
llm_context/cli.py
llm_context/cmd_pipeline.py
llm_context/commands.py
llm_context/context_generator.py
llm_context/context_preview.py
llm_context/context_spec.py
llm_context/exceptions.py
llm_context/exec_env.py
llm_context/file_selector.py
llm_context/mcp.py
llm_context/overviews.py
llm_context/project_setup.py
llm_context/rule.py
llm_context/rule_parser.py
llm_context/state.py
llm_context/utils.py
llm_context/excerpters/base.py
llm_context/excerpters/code_outliner.py
llm_context/excerpters/language_mapping.py
llm_context/excerpters/markdown.py
llm_context/excerpters/parser.py
llm_context/excerpters/service.py
llm_context/excerpters/sfc.py
llm_context/excerpters/tagger.py
llm_context/excerpters/ts-qry/README.md
llm_context/excerpters/ts-qry/c-tags.scm
llm_context/excerpters/ts-qry/cpp-tags.scm
llm_context/excerpters/ts-qry/csharp-tags.scm
llm_context/excerpters/ts-qry/elisp-tags.scm
llm_context/excerpters/ts-qry/elixir-tags.scm
llm_context/excerpters/ts-qry/elm-tags.scm
llm_context/excerpters/ts-qry/go-tags.scm
llm_context/excerpters/ts-qry/java-tags.scm
llm_context/excerpters/ts-qry/javascript-tags.scm
llm_context/excerpters/ts-qry/markdown.scm
llm_context/excerpters/ts-qry/php-tags.scm
llm_context/excerpters/ts-qry/python-tags.scm
llm_context/excerpters/ts-qry/ruby-tags.scm
llm_context/excerpters/ts-qry/rust-tags.scm
llm_context/excerpters/ts-qry/svelte-injections.scm
llm_context/excerpters/ts-qry/typescript-tags.scm
llm_context/lc_resources/dotgitignore
llm_context/lc_resources/completions/bash-completion.sh
llm_context/lc_resources/completions/zsh-completion.zsh
llm_context/lc_resources/rules/lc/exc-base.md
llm_context/lc_resources/rules/lc/flt-base.md
llm_context/lc_resources/rules/lc/flt-no-files.md
llm_context/lc_resources/rules/lc/flt-no-full.md
llm_context/lc_resources/rules/lc/flt-no-outline.md
llm_context/lc_resources/rules/lc/ins-developer.md
llm_context/lc_resources/rules/lc/ins-rule-framework.md
llm_context-0.6.1.dist-info/METADATA
llm_context-0.6.1.dist-info/WHEEL
llm_context-0.6.1.dist-info/entry_points.txt
llm_context-0.6.1.dist-info/licenses/LICENSE
llm_context-0.6.1.dist-info/RECORD
