Metadata-Version: 2.4
Name: llm-context
Version: 0.6.1
Summary: Share code with LLMs via Model Context Protocol or clipboard. Rule-based customization enables easy switching between different tasks (like code review and documentation). Code outlining support is included as a standard feature.
Project-URL: Repository, https://github.com/cyberchitta/llm-context.py
Project-URL: User Guide, https://github.com/cyberchitta/llm-context.py/blob/main/docs/user-guide.md
Project-URL: Changelog, https://github.com/cyberchitta/llm-context.py/blob/main/CHANGELOG.md
Author-email: restlessronin <88921269+restlessronin@users.noreply.github.com>
License-Expression: Apache-2.0
License-File: LICENSE
Keywords: ai,chat,clipboard,code,context,llm
Classifier: Development Status :: 4 - Beta
Classifier: Environment :: Console
Classifier: Intended Audience :: Developers
Classifier: Intended Audience :: Information Technology
Classifier: Intended Audience :: Science/Research
Classifier: Topic :: Communications :: Chat
Classifier: Topic :: Scientific/Engineering :: Artificial Intelligence
Classifier: Topic :: Software Development :: Code Generators
Classifier: Topic :: Utilities
Requires-Python: >=3.12
Requires-Dist: jinja2<4.0,>=3.1.6
Requires-Dist: mcp>=1.26.0
Requires-Dist: packaging<27.0,>=26.0
Requires-Dist: pathspec>=1.0.4
Requires-Dist: pyperclip<2.0.0,>=1.11.0
Requires-Dist: python-multipart>=0.0.22
Requires-Dist: pyyaml>=6.0.3
Requires-Dist: starlette>=0.49.1
Requires-Dist: tree-sitter-language-pack>=0.13.0
Requires-Dist: tree-sitter>=0.25.2
